LICENSE
MANIFEST.in
README.md
requirements.txt
setup.cfg
setup.py
Adept.egg-info/PKG-INFO
Adept.egg-info/SOURCES.txt
Adept.egg-info/dependency_links.txt
Adept.egg-info/requires.txt
Adept.egg-info/top_level.txt
adept/__init__.py
adept/errors.py