Metadata-Version: 1.1
Name: Adept
Version: 0.0.2
Summary: Simple binding for Adept
Home-page: https://github.com/fictivekin/adept-python
Author: Phil Howell
Author-email: phil@fictivekin.com
License: MIT
Download-URL: https://github.com/fictivekin/adept-python/archive/0.0.2.tar.gz
Keywords: adept,image,resize,processing
Platform: UNKNOWN
Classifier: Environment :: Web Environment
Classifier: Intended Audience :: Developers
Classifier: Development Status :: 2 - Pre-Alpha
Classifier: Operating System :: OS Independent
Classifier: License :: OSI Approved :: BSD License
Classifier: Programming Language :: Python
Classifier: Topic :: Multimedia :: Graphics :: Graphics Conversion
Classifier: Topic :: Internet :: WWW/HTTP :: Dynamic Content
Classifier: Topic :: Software Development :: Libraries :: Python Modules
